[{"Message":"где покупки обычных боксов","UserProfile":"rbxthumb://type=AvatarHeadShot&id=1408423460&w=100&h=100","Name":"K20arina","Rank":"User"},{"Message":"я 100 снежинок обменяла на моне","Name":"pmshkas","UserProfile":"rbxthumb://type=AvatarHeadShot&id=5082276831&w=100&h=100","Rank":"User"},{"Message":"ты не посмотрев блять","UserProfile":"rbxthumb://type=AvatarHeadShot&id=5082276831&w=100&h=100","Name":"pmshkas","Rank":"User"},{"Message":"не*...","Name":"pmshkas","UserProfile":"rbxthumb://type=AvatarHeadShot&id=5082276831&w=100&h=100","Rank":"User"},{"Message":"@pmshkas сколько у тебя снежинок","UserProfile":"rbxthumb://type=AvatarHeadShot&id=3955511698&w=100&h=100","Name":"explorersf","Rank":"Premium"},{"Message":"yo","Name":"Grumpygravyyl","UserProfile":"rbxthumb://type=AvatarHeadShot&id=4044893487&w=100&h=100","Rank":"User"},{"Message":"ê","UserProfile":"rbxthumb://type=AvatarHeadShot&id=5126351289&w=100&h=100","Name":"khangchuche7","Rank":"User"},{"Message":"..","Name":"K20arina","UserProfile":"rbxthumb://type=AvatarHeadShot&id=1408423460&w=100&h=100","Rank":"User"},{"Message":"ребят, а как сделать что бы не вводить никогда заново ключ от флюксуса?","UserProfile":"rbxthumb://type=AvatarHeadShot&id=2268621469&w=100&h=100","Name":"AllexYuzh","Rank":"Premium"},{"Message":"новый скачать","Name":"FEDGOD12","UserProfile":"rbxthumb://type=AvatarHeadShot&id=1897578673&w=100&h=100","Rank":"User"},{"Message":"никак, каждый день он сбрасывается","UserProfile":"rbxthumb://type=AvatarHeadShot&id=5245925389&w=100&h=100","Name":"MegaSobiralka","Rank":"User"},{"Message":"у меня","Name":"pmshkas","UserProfile":"rbxthumb://type=AvatarHeadShot&id=5082276831&w=100&h=100","Rank":"User"},{"Message":"60","UserProfile":"rbxthumb://type=AvatarHeadShot&id=5082276831&w=100&h=100","Name":"pmshkas","Rank":"User"},{"Message":"к","Name":"pmshkas","UserProfile":"rbxthumb://type=AvatarHeadShot&id=5082276831&w=100&h=100","Rank":"User"},{"Message":"у меня не надо ключ получать","UserProfile":"rbxthumb://type=AvatarHeadShot&id=1897578673&w=100&h=100","Name":"FEDGOD12","Rank":"User"},{"Message":"у меня только 9к будет, я на ночь оставила тел ,а там уже через минут 10 села зарядка/","Name":"K20arina","UserProfile":"rbxthumb://type=AvatarHeadShot&id=1408423460&w=100&h=100","Rank":"User"},{"Message":"АХАХАХАХА А У МЯ ИНЕТ СЛЕТЕЛ КАК ТОЛЬКО Я ЗАСНУЛА","UserProfile":"rbxthumb://type=AvatarHeadShot&id=5082276831&w=100&h=100","Name":"pmshkas","Rank":"User"},{"Message":"АХАХАХХАХСХСХАХХААХХАХАХАА","Name":"K20arina","UserProfile":"rbxthumb://type=AvatarHeadShot&id=1408423460&w=100&h=100","Rank":"User"},{"Message":"АХАХПХПХ ","UserProfile":"rbxthumb://type=AvatarHeadShot&id=3955511698&w=100&h=100","Name":"explorersf","Rank":"Premium"},{"Message":"МОЩНО СЛИШКОМ ","Name":"K20arina","UserProfile":"rbxthumb://type=AvatarHeadShot&id=1408423460&w=100&h=100","Rank":"User"},{"Message":"плаа,у меня будет перерождение с человеческой жизни на тапка ,если я не соберу до конца обновы хотя бы 80к","UserProfile":"rbxthumb://type=AvatarHeadShot&id=1408423460&w=100&h=100","Name":"K20arina","Rank":"User"},{"Message":"у мя не показывает последнюю стоочку💔💔","Name":"pmshkas","UserProfile":"rbxthumb://type=AvatarHeadShot&id=5082276831&w=100&h=100","Rank":"User"},{"Message":"и у мяяя..","UserProfile":"rbxthumb://type=AvatarHeadShot&id=1408423460&w=100&h=100","Name":"K20arina","Rank":"User"},{"Message":"я забыла что таммм","Name":"K20arina","UserProfile":"rbxthumb://type=AvatarHeadShot&id=1408423460&w=100&h=100","Rank":"User"},{"Message":"ХАХАХХАХАХА","UserProfile":"rbxthumb://type=AvatarHeadShot&id=1408423460&w=100&h=100","Name":"K20arina","Rank":"User"},{"Message":"😦","Name":"pmshkas","UserProfile":"rbxthumb://type=AvatarHeadShot&id=5082276831&w=100&h=100","Rank":"User"},{"Message":"bypass end","UserProfile":"rbxthumb://type=AvatarHeadShot&id=3754263419&w=100&h=100","Name":"EeMe6i","Rank":"Premium"},{"Message":"мне напиздели что обнову уберут завтра","Name":"pmshkas","UserProfile":"rbxthumb://type=AvatarHeadShot&id=5082276831&w=100&h=100","Rank":"User"},{"Message":"может быть в феврале","UserProfile":"rbxthumb://type=AvatarHeadShot&id=2268621469&w=100&h=100","Name":"AllexYuzh","Rank":"Premium"},{"Message":"20 январь","Name":"explorersf","UserProfile":"rbxthumb://type=AvatarHeadShot&id=3955511698&w=100&h=100","Rank":"Premium"},{"Message":"а где сказали","UserProfile":"rbxthumb://type=AvatarHeadShot&id=2268621469&w=100&h=100","Name":"AllexYuzh","Rank":"Premium"}]