[{"Message":"nigger","UserProfile":"rbxthumb://type=AvatarHeadShot&id=3748856283&w=100&h=100","Name":"PetSimXplayer_975","Rank":"Premium"},{"Message":"stupid monkeys don't know how to speak english","Name":"olusolab","UserProfile":"rbxthumb://type=AvatarHeadShot&id=1338432120&w=100&h=100","Rank":"Premium"},{"Message":"bro stfu","UserProfile":"rbxthumb://type=AvatarHeadShot&id=3674061049&w=100&h=100","Name":"Migelj838","Rank":"User"},{"Message":"I know 7 languages ","Name":"Migelj838","UserProfile":"rbxthumb://type=AvatarHeadShot&id=3674061049&w=100&h=100","Rank":"User"},{"Message":"hi","UserProfile":"rbxthumb://type=AvatarHeadShot&id=2210844014&w=100&h=100","Name":"XxAAndrew_xX","Rank":"User"},{"Message":"пацаны кто фармит?)))","Name":"shadowfiend_techies","UserProfile":"rbxthumb://type=AvatarHeadShot&id=3976258049&w=100&h=100","Rank":"User"},{"Message":"HEY","UserProfile":"rbxthumb://type=AvatarHeadShot&id=2282221168&w=100&h=100","Name":"Gamer37657","Rank":"User"},{"Message":"10k..","Name":"Migelj838","UserProfile":"rbxthumb://type=AvatarHeadShot&id=3674061049&w=100&h=100","Rank":"User"},{"Message":"u sffu","UserProfile":"rbxthumb://type=AvatarHeadShot&id=1338432120&w=100&h=100","Name":"olusolab","Rank":"Premium"},{"Message":"92к..","Name":"ki1xql","UserProfile":"rbxthumb://type=AvatarHeadShot&id=3692463286&w=100&h=100","Rank":"User"},{"Message":"\"sffu\" бро не знает писать","UserProfile":"rbxthumb://type=AvatarHeadShot&id=3674061049&w=100&h=100","Name":"Migelj838","Rank":"User"},{"Message":"83к","Name":"haz3mn22850","UserProfile":"rbxthumb://type=AvatarHeadShot&id=5105172847&w=100&h=100","Rank":"User"},{"Message":"o","UserProfile":"rbxthumb://type=AvatarHeadShot&id=318044392&w=100&h=100","Name":"greedygirl29","Rank":"User"},{"Message":"oi","Name":"eunaousohappymode","UserProfile":"rbxthumb://type=AvatarHeadShot&id=3817024917&w=100&h=100","Rank":"User"},{"Message":"извините, вас бачили за чити?","UserProfile":"rbxthumb://type=AvatarHeadShot&id=2900797940&w=100&h=100","Name":"luhok_rbx","Rank":"User"},{"Message":"банили?","Name":"luhok_rbx","UserProfile":"rbxthumb://type=AvatarHeadShot&id=2900797940&w=100&h=100","Rank":"User"},{"Message":"11к..","UserProfile":"rbxthumb://type=AvatarHeadShot&id=3674061049&w=100&h=100","Name":"Migelj838","Rank":"User"},{"Message":"ТА КАК ТА БЫСТРО?","Name":"luhok_rbx","UserProfile":"rbxthumb://type=AvatarHeadShot&id=2900797940&w=100&h=100","Rank":"User"},{"Message":"lol","UserProfile":"rbxthumb://type=AvatarHeadShot&id=2464972346&w=100&h=100","Name":"darisljes2025","Rank":"User"},{"Message":"hi","Name":"eunaousohappymode","UserProfile":"rbxthumb://type=AvatarHeadShot&id=3817024917&w=100&h=100","Rank":"User"},{"Message":"С НОВЫЙ ГОДОМ!!!!","UserProfile":"rbxthumb://type=AvatarHeadShot&id=3674061049&w=100&h=100","Name":"Migelj838","Rank":"User"},{"Message":"дааа","Name":"ki1xql","UserProfile":"rbxthumb://type=AvatarHeadShot&id=3692463286&w=100&h=100","Rank":"User"},{"Message":"HI KAYLAAAAA","UserProfile":"rbxthumb://type=AvatarHeadShot&id=335489653&w=100&h=100","Name":"EREN008YT","Rank":"User"},{"Message":"hola lucas","Name":"EREN008YT","UserProfile":"rbxthumb://type=AvatarHeadShot&id=335489653&w=100&h=100","Rank":"User"},{"Message":"hi","UserProfile":"rbxthumb://type=AvatarHeadShot&id=3217031547&w=100&h=100","Name":"d7omnx905gg","Rank":"User"},{"Message":"люди какой шанс что забанят? ","Name":"sffffhbvfjn","UserProfile":"rbxthumb://type=AvatarHeadShot&id=5361575925&w=100&h=100","Rank":"User"},{"Message":"незнаю, 93к у меня норм уже, ак дон","UserProfile":"rbxthumb://type=AvatarHeadShot&id=3692463286&w=100&h=100","Name":"ki1xql","Rank":"User"},{"Message":"сколько фармишь? ","Name":"sffffhbvfjn","UserProfile":"rbxthumb://type=AvatarHeadShot&id=5361575925&w=100&h=100","Rank":"User"},{"Message":"how to not get kicked","UserProfile":"rbxthumb://type=AvatarHeadShot&id=746573521&w=100&h=100","Name":"ronaldojuniou","Rank":"User"},{"Message":"т","Name":"Artur521Lol2022","UserProfile":"rbxthumb://type=AvatarHeadShot&id=3190963862&w=100&h=100","Rank":"User"},{"Message":"с нг","UserProfile":"rbxthumb://type=AvatarHeadShot&id=4022128693&w=100&h=100","Name":"itz_lizo4ka11","Rank":"User"}]