[{"Message":"а а  а а а а а а а а ","UserProfile":"rbxthumb://type=AvatarHeadShot&id=4061843574&w=100&h=100","Name":"qwzxwes","Rank":"User"},{"Message":"я школьницу ей нос пробил это мало","Name":"9rryuffu","UserProfile":"rbxthumb://type=AvatarHeadShot&id=2897823294&w=100&h=100","Rank":"User"},{"Message":"idk","UserProfile":"rbxthumb://type=AvatarHeadShot&id=3812836519&w=100&h=100","Name":"Kobe_Vco2","Rank":"Premium"},{"Message":"какие то немощь орут","Name":"9rryuffu","UserProfile":"rbxthumb://type=AvatarHeadShot&id=2897823294&w=100&h=100","Rank":"User"},{"Message":"Russian group kid, get a father kids.","UserProfile":"rbxthumb://type=AvatarHeadShot&id=3614297224&w=100&h=100","Name":"gamer_kunj29","Rank":"Premium"},{"Message":"у  мя ","Name":"SashaAndDanyaLOX","UserProfile":"rbxthumb://type=AvatarHeadShot&id=4355890381&w=100&h=100","Rank":"User"},{"Message":"а у вас чо","UserProfile":"rbxthumb://type=AvatarHeadShot&id=4355890381&w=100&h=100","Name":"SashaAndDanyaLOX","Rank":"User"},{"Message":"37 к монет и пасс куплен","Name":"SashaAndDanyaLOX","UserProfile":"rbxthumb://type=AvatarHeadShot&id=4355890381&w=100&h=100","Rank":"User"},{"Message":"yo","UserProfile":"rbxthumb://type=AvatarHeadShot&id=3513759333&w=100&h=100","Name":"kareemMohamed_b","Rank":"User"},{"Message":"nigaa","Name":"3CDx70x","UserProfile":"rbxthumb://type=AvatarHeadShot&id=5375220072&w=100&h=100","Rank":"User"},{"Message":"ого, как так быстро? ","UserProfile":"rbxthumb://type=AvatarHeadShot&id=4355890381&w=100&h=100","Name":"SashaAndDanyaLOX","Rank":"User"},{"Message":"hi","Name":"baconhairnoob777774","UserProfile":"rbxthumb://type=AvatarHeadShot&id=2241070315&w=100&h=100","Rank":"User"},{"Message":"hello","UserProfile":"rbxthumb://type=AvatarHeadShot&id=3850592092&w=100&h=100","Name":"jnxqil","Rank":"Premium"},{"Message":"у меня 55к + весь пасс","Name":"dicuifjeciuiu","UserProfile":"rbxthumb://type=AvatarHeadShot&id=1878802729&w=100&h=100","Rank":"User"},{"Message":"balls","UserProfile":"rbxthumb://type=AvatarHeadShot&id=3695378425&w=100&h=100","Name":"ColRidlE","Rank":"User"},{"Message":"о это мне в тгк прислал?","Name":"pipuka_Artem","UserProfile":"rbxthumb://type=AvatarHeadShot&id=2266282159&w=100&h=100","Rank":"User"},{"Message":"french pls-","UserProfile":"rbxthumb://type=AvatarHeadShot&id=3020971223&w=100&h=100","Name":"SQUEAK519yt","Rank":"User"},{"Message":"как дела у вас","Name":"qwixxp_1","UserProfile":"rbxthumb://type=AvatarHeadShot&id=3889470677&w=100&h=100","Rank":"Premium"},{"Message":"а","UserProfile":"rbxthumb://type=AvatarHeadShot&id=3889470677&w=100&h=100","Name":"qwixxp_1","Rank":"Premium"},{"Message":"нармана","Name":"12Mev12","UserProfile":"rbxthumb://type=AvatarHeadShot&id=3074123365&w=100&h=100","Rank":"Premium"},{"Message":"шо за суета","UserProfile":"rbxthumb://type=AvatarHeadShot&id=1056094344&w=100&h=100","Name":"Gshs521","Rank":"Premium"},{"Message":"хо","Name":"HelloKitti8953","UserProfile":"rbxthumb://type=AvatarHeadShot&id=2872316736&w=100&h=100","Rank":"User"},{"Message":"хорошо","UserProfile":"rbxthumb://type=AvatarHeadShot&id=2872316736&w=100&h=100","Name":"HelloKitti8953","Rank":"User"},{"Message":"шо ты сказала","Name":"pipuka_Artem","UserProfile":"rbxthumb://type=AvatarHeadShot&id=2266282159&w=100&h=100","Rank":"User"},{"Message":"день 5","UserProfile":"rbxthumb://type=AvatarHeadShot&id=4539946805&w=100&h=100","Name":"Yyour_bestfriend","Rank":"User"},{"Message":"Доброе утро опять","Name":"Yyour_bestfriend","UserProfile":"rbxthumb://type=AvatarHeadShot&id=4539946805&w=100&h=100","Rank":"User"},{"Message":"еба","UserProfile":"rbxthumb://type=AvatarHeadShot&id=3549048382&w=100&h=100","Name":"3ae4ka_Sasha","Rank":"User"},{"Message":"РОССИЯ🇷🇺🇷🇺🇷🇺","Name":"3ae4ka_Sasha","UserProfile":"rbxthumb://type=AvatarHeadShot&id=3549048382&w=100&h=100","Rank":"User"},{"Message":"приф все ","UserProfile":"rbxthumb://type=AvatarHeadShot&id=2493277334&w=100&h=100","Name":"Robloxian9287109","Rank":"User"},{"Message":"салам ","Name":"3ae4ka_Sasha","UserProfile":"rbxthumb://type=AvatarHeadShot&id=3549048382&w=100&h=100","Rank":"User"},{"Message":"я мурдер","UserProfile":"rbxthumb://type=AvatarHeadShot&id=2493277334&w=100&h=100","Name":"Robloxian9287109","Rank":"User"}]