[{"Message":"Brl ","UserProfile":"rbxthumb://type=AvatarHeadShot&id=2449904911&w=100&h=100","Name":"Xar_MzA","Rank":"Premium"},{"Message":"Chat ain't work","Name":"Xar_MzA","UserProfile":"rbxthumb://type=AvatarHeadShot&id=2449904911&w=100&h=100","Rank":"Premium"},{"Message":"wat","UserProfile":"rbxthumb://type=AvatarHeadShot&id=2449904911&w=100&h=100","Name":"Xar_MzA","Rank":"Premium"},{"Message":"hello","Name":"Xar_MzA","UserProfile":"rbxthumb://type=AvatarHeadShot&id=2449904911&w=100&h=100","Rank":"Premium"},{"Message":"wasdup fams","UserProfile":"rbxthumb://type=AvatarHeadShot&id=1592970855&w=100&h=100","Name":"Alengeney","Rank":"Premium"},{"Message":"yo","Name":"Alengeney","UserProfile":"rbxthumb://type=AvatarHeadShot&id=1592970855&w=100&h=100","Rank":"Premium"},{"Message":"how yall days going","UserProfile":"rbxthumb://type=AvatarHeadShot&id=1592970855&w=100&h=100","Name":"Alengeney","Rank":"Premium"},{"Message":"sjs","Name":"Alengeney","UserProfile":"rbxthumb://type=AvatarHeadShot&id=1592970855&w=100&h=100","Rank":"Premium"},{"Message":"we good","UserProfile":"rbxthumb://type=AvatarHeadShot&id=746573521&w=100&h=100","Name":"ronaldojuniou","Rank":"User"},{"Message":"bi","Name":"TILERISA","UserProfile":"rbxthumb://type=AvatarHeadShot&id=5347376446&w=100&h=100","Rank":"User"},{"Message":"15,","UserProfile":"rbxthumb://type=AvatarHeadShot&id=5281640948&w=100&h=100","Name":"qwinikxi","Rank":"User"},{"Message":"15,352к","Name":"qwinikxi","UserProfile":"rbxthumb://type=AvatarHeadShot&id=5281640948&w=100&h=100","Rank":"User"},{"Message":"108к","UserProfile":"rbxthumb://type=AvatarHeadShot&id=4291725459&w=100&h=100","Name":"qwelovme","Rank":"User"},{"Message":"с пассом 108к?","Name":"KILLMONST001","UserProfile":"rbxthumb://type=AvatarHeadShot&id=4380565532&w=100&h=100","Rank":"User"},{"Message":"у меня с пассом у нее хс","UserProfile":"rbxthumb://type=AvatarHeadShot&id=5281640948&w=100&h=100","Name":"qwinikxi","Rank":"User"},{"Message":"у меня 26к с пассом","Name":"KILLMONST001","UserProfile":"rbxthumb://type=AvatarHeadShot&id=4380565532&w=100&h=100","Rank":"User"},{"Message":"и 3 подарка","UserProfile":"rbxthumb://type=AvatarHeadShot&id=4257329022&w=100&h=100","Name":"el7xerix_top","Rank":"User"},{"Message":"ой","Name":"el7xerix_top","UserProfile":"rbxthumb://type=AvatarHeadShot&id=4257329022&w=100&h=100","Rank":"User"},{"Message":"кто сколько за ночь фармил с этим скриптом?","UserProfile":"rbxthumb://type=AvatarHeadShot&id=4257329022&w=100&h=100","Name":"el7xerix_top","Rank":"User"},{"Message":"я потом когда винтовку куплю буду 80к копить на подарки ","Name":"KILLMONST001","UserProfile":"rbxthumb://type=AvatarHeadShot&id=4380565532&w=100&h=100","Rank":"User"},{"Message":"у меня ночью не получается почему то выгоняет за афк 20 минут","UserProfile":"rbxthumb://type=AvatarHeadShot&id=4380565532&w=100&h=100","Name":"KILLMONST001","Rank":"User"},{"Message":"я ночью с другим скриптом","Name":"KILLMONST001","UserProfile":"rbxthumb://type=AvatarHeadShot&id=4380565532&w=100&h=100","Rank":"User"},{"Message":"каким","UserProfile":"rbxthumb://type=AvatarHeadShot&id=5281640948&w=100&h=100","Name":"qwinikxi","Rank":"User"},{"Message":"от торы","Name":"KILLMONST001","UserProfile":"rbxthumb://type=AvatarHeadShot&id=4380565532&w=100&h=100","Rank":"User"},{"Message":".","UserProfile":"rbxthumb://type=AvatarHeadShot&id=4257329022&w=100&h=100","Name":"el7xerix_top","Rank":"User"},{"Message":"напиши пж тут скрипт","Name":"qwinikxi","UserProfile":"rbxthumb://type=AvatarHeadShot&id=5281640948&w=100&h=100","Rank":"User"},{"Message":"так полностью не влезет ","UserProfile":"rbxthumb://type=AvatarHeadShot&id=4380565532&w=100&h=100","Name":"KILLMONST001","Rank":"User"},{"Message":"пля напиши в ЛС в тг ща ник дам","Name":"qwinikxi","UserProfile":"rbxthumb://type=AvatarHeadShot&id=5281640948&w=100&h=100","Rank":"User"},{"Message":"не мне лень ввходи","UserProfile":"rbxthumb://type=AvatarHeadShot&id=4380565532&w=100&h=100","Name":"KILLMONST001","Rank":"User"},{"Message":"выходить","Name":"KILLMONST001","UserProfile":"rbxthumb://type=AvatarHeadShot&id=4380565532&w=100&h=100","Rank":"User"},{"Message":"может быть потом","UserProfile":"rbxthumb://type=AvatarHeadShot&id=4380565532&w=100&h=100","Name":"KILLMONST001","Rank":"User"}]