[{"Message":"lol","UserProfile":"rbxthumb://type=AvatarHeadShot&id=2647669413&w=100&h=100","Name":"piggyfan1233456","Rank":"Premium"},{"Message":"When this script update?","Name":"chartoorw","UserProfile":"rbxthumb://type=AvatarHeadShot&id=5352206067&w=100&h=100","Rank":"User"},{"Message":"hello?","UserProfile":"rbxthumb://type=AvatarHeadShot&id=5352206067&w=100&h=100","Name":"chartoorw","Rank":"User"},{"Message":"hi","Name":"LIPEMDM14","UserProfile":"rbxthumb://type=AvatarHeadShot&id=2843543139&w=100&h=100","Rank":"Premium"},{"Message":"Pls farm snowflake","UserProfile":"rbxthumb://type=AvatarHeadShot&id=2843543139&w=100&h=100","Name":"LIPEMDM14","Rank":"Premium"},{"Message":"pls when farm token im so tired","Name":"Sh1ver1ngs0uls","UserProfile":"rbxthumb://type=AvatarHeadShot&id=5001626063&w=100&h=100","Rank":"User"},{"Message":"I NEED UPDATE SCRIPT FOR MM2","UserProfile":"rbxthumb://type=AvatarHeadShot&id=5157060746&w=100&h=100","Name":"newflozzera","Rank":"User"},{"Message":"the free ability could work ","Name":"bobo63363","UserProfile":"rbxthumb://type=AvatarHeadShot&id=4549870504&w=100&h=100","Rank":"User"},{"Message":"autofarm is broken","UserProfile":"rbxthumb://type=AvatarHeadShot&id=3869777521&w=100&h=100","Name":"bWare_murdr","Rank":"Premium"},{"Message":"realy?","Name":"bobo63363","UserProfile":"rbxthumb://type=AvatarHeadShot&id=4549870504&w=100&h=100","Rank":"User"},{"Message":"it doesn't work anymore lol","UserProfile":"rbxthumb://type=AvatarHeadShot&id=3869777521&w=100&h=100","Name":"bWare_murdr","Rank":"Premium"},{"Message":"because its not update not? n","Name":"TetraPhase","UserProfile":"rbxthumb://type=AvatarHeadShot&id=1795430803&w=100&h=100","Rank":"Premium"},{"Message":"Symphony No updated??","UserProfile":"rbxthumb://type=AvatarHeadShot&id=4549870504&w=100&h=100","Name":"bobo63363","Rank":"User"},{"Message":"ALL ALRIGHT BUT AUTO FARM NED TO UPDATE pls be patieng","Name":"TetraPhase","UserProfile":"rbxthumb://type=AvatarHeadShot&id=1795430803&w=100&h=100","Rank":"Premium"},{"Message":"@everyom","UserProfile":"rbxthumb://type=AvatarHeadShot&id=1795430803&w=100&h=100","Name":"TetraPhase","Rank":"Premium"},{"Message":"auto farm will release tommorow","Name":"TetraPhase","UserProfile":"rbxthumb://type=AvatarHeadShot&id=1795430803&w=100&h=100","Rank":"Premium"},{"Message":"bruhh","UserProfile":"rbxthumb://type=AvatarHeadShot&id=5001626063&w=100&h=100","Name":"Sh1ver1ngs0uls","Rank":"User"},{"Message":"@everyone MM2 AUTO FARM HAS BEEN POSTED","Name":"TetraPhase","UserProfile":"rbxthumb://type=AvatarHeadShot&id=1795430803&w=100&h=100","Rank":"Premium"},{"Message":"@","UserProfile":"rbxthumb://type=AvatarHeadShot&id=1795430803&w=100&h=100","Name":"TetraPhase","Rank":"Premium"},{"Message":"REJOIK SYMPVONT HUB @EVERYONE","Name":"TetraPhase","UserProfile":"rbxthumb://type=AvatarHeadShot&id=1795430803&w=100&h=100","Rank":"Premium"},{"Message":"The Christmas auto farm has been released @everyone","UserProfile":"rbxthumb://type=AvatarHeadShot&id=1795430803&w=100&h=100","Name":"TetraPhase","Rank":"Premium"},{"Message":":D","Name":"LIPEMDM14","UserProfile":"rbxthumb://type=AvatarHeadShot&id=2843543139&w=100&h=100","Rank":"Premium"},{"Message":"w update. ","UserProfile":"rbxthumb://type=AvatarHeadShot&id=3869777521&w=100&h=100","Name":"bWare_murdr","Rank":"Premium"},{"Message":"yuck","Name":"Sh1ver1ngs0uls","UserProfile":"rbxthumb://type=AvatarHeadShot&id=5001626063&w=100&h=100","Rank":"User"},{"Message":"Lol","UserProfile":"rbxthumb://type=AvatarHeadShot&id=3726442593&w=100&h=100","Name":"N0tt_Sergiu","Rank":"Premium"},{"Message":"bro why does it only say 40 max even if its 50 u have to do it manually if its 50🙄🙄","Name":"Sh1ver1ngs0uls","UserProfile":"rbxthumb://type=AvatarHeadShot&id=5001626063&w=100&h=100","Rank":"User"},{"Message":"BRO ITS BUGGED THAT FAST WTH","UserProfile":"rbxthumb://type=AvatarHeadShot&id=5001626063&w=100&h=100","Name":"Sh1ver1ngs0uls","Rank":"User"},{"Message":"Really","Name":"LIPEMDM14","UserProfile":"rbxthumb://type=AvatarHeadShot&id=2843543139&w=100&h=100","Rank":"Premium"},{"Message":"yeah i tried for 2 rounds and it work but on 3rd it wont farm","UserProfile":"rbxthumb://type=AvatarHeadShot&id=5001626063&w=100&h=100","Name":"Sh1ver1ngs0uls","Rank":"User"},{"Message":"yoo","Name":"Zara_sofea1315","UserProfile":"rbxthumb://type=AvatarHeadShot&id=3025881583&w=100&h=100","Rank":"User"},{"Message":"yoo cunts","UserProfile":"rbxthumb://type=AvatarHeadShot&id=4018872984&w=100&h=100","Name":"not_joella123","Rank":"User"}]