[{"Message":"hi","UserProfile":"rbxthumb://type=AvatarHeadShot&id=5196404116&w=100&h=100","Name":"qw3rtydax","Rank":"User"},{"Message":"I love this script","Name":"greenshop_36","UserProfile":"rbxthumb://type=AvatarHeadShot&id=5101282518&w=100&h=100","Rank":"User"},{"Message":"me too ","UserProfile":"rbxthumb://type=AvatarHeadShot&id=4531155496&w=100&h=100","Name":"akohrd","Rank":"User"},{"Message":"wassup my bitch ass niggas","Name":"qw3rtydax","UserProfile":"rbxthumb://type=AvatarHeadShot&id=5196404116&w=100&h=100","Rank":"User"},{"Message":"wsg niggas","UserProfile":"rbxthumb://type=AvatarHeadShot&id=5196404116&w=100&h=100","Name":"qw3rtydax","Rank":"User"},{"Message":"cool","Name":"KRAZYOFICIALGAMER","UserProfile":"rbxthumb://type=AvatarHeadShot&id=2342071364&w=100&h=100","Rank":"Premium"},{"Message":"aoba","UserProfile":"rbxthumb://type=AvatarHeadShot&id=2342071364&w=100&h=100","Name":"KRAZYOFICIALGAMER","Rank":"Premium"},{"Message":"shut thw fuck up nigger","Name":"Samhaveasuperchair","UserProfile":"rbxthumb://type=AvatarHeadShot&id=4775132590&w=100&h=100","Rank":"User"},{"Message":"shut the fuck up","UserProfile":"rbxthumb://type=AvatarHeadShot&id=4775132590&w=100&h=100","Name":"Samhaveasuperchair","Rank":"User"},{"Message":"nigga","Name":"Samhaveasuperchair","UserProfile":"rbxthumb://type=AvatarHeadShot&id=4775132590&w=100&h=100","Rank":"User"},{"Message":"hello","UserProfile":"rbxthumb://type=AvatarHeadShot&id=2737529113&w=100&h=100","Name":"karar234u","Rank":"User"},{"Message":"hello","Name":"huikvf234","UserProfile":"rbxthumb://type=AvatarHeadShot&id=3352868185&w=100&h=100","Rank":"Premium"},{"Message":"Ima black knee girl","UserProfile":"rbxthumb://type=AvatarHeadShot&id=5030235986&w=100&h=100","Name":"bstplayerbladeball","Rank":"User"},{"Message":"hello niggas","Name":"deniztrban","UserProfile":"rbxthumb://type=AvatarHeadShot&id=3739293499&w=100&h=100","Rank":"User"},{"Message":"yo i love this script ik trolling people with the fake gun","UserProfile":"rbxthumb://type=AvatarHeadShot&id=3513759333&w=100&h=100","Name":"kareemMohamed_b","Rank":"User"},{"Message":"hello :)","Name":"saeki2joints","UserProfile":"rbxthumb://type=AvatarHeadShot&id=3409328794&w=100&h=100","Rank":"User"},{"Message":"bro u dont need fake gun use conq haki","UserProfile":"rbxthumb://type=AvatarHeadShot&id=3739293499&w=100&h=100","Name":"deniztrban","Rank":"User"},{"Message":"MOTHERFUCKER","Name":"deniztrban","UserProfile":"rbxthumb://type=AvatarHeadShot&id=3739293499&w=100&h=100","Rank":"User"},{"Message":"can i swear","UserProfile":"rbxthumb://type=AvatarHeadShot&id=5030235986&w=100&h=100","Name":"bstplayerbladeball","Rank":"User"},{"Message":"yesss","Name":"deniztrban","UserProfile":"rbxthumb://type=AvatarHeadShot&id=3739293499&w=100&h=100","Rank":"User"},{"Message":"AS YOU CAN SEE I TYPED FUCK NIGGA","UserProfile":"rbxthumb://type=AvatarHeadShot&id=3739293499&w=100&h=100","Name":"deniztrban","Rank":"User"},{"Message":"ITS L","Name":"deniztrban","UserProfile":"rbxthumb://type=AvatarHeadShot&id=3739293499&w=100&h=100","Rank":"User"},{"Message":"WHO WA","UserProfile":"rbxthumb://type=AvatarHeadShot&id=3739293499&w=100&h=100","Name":"deniztrban","Rank":"User"},{"Message":"WHO WANT","Name":"deniztrban","UserProfile":"rbxthumb://type=AvatarHeadShot&id=3739293499&w=100&h=100","Rank":"User"},{"Message":"SEXX","UserProfile":"rbxthumb://type=AvatarHeadShot&id=3739293499&w=100&h=100","Name":"deniztrban","Rank":"User"},{"Message":"SEXXMAA","Name":"deniztrban","UserProfile":"rbxthumb://type=AvatarHeadShot&id=3739293499&w=100&h=100","Rank":"User"},{"Message":"uzing pull","UserProfile":"rbxthumb://type=AvatarHeadShot&id=3411633672&w=100&h=100","Name":"yup10034","Rank":"User"},{"Message":"hi","Name":"fgpqpqht21212","UserProfile":"rbxthumb://type=AvatarHeadShot&id=4039873855&w=100&h=100","Rank":"Premium"},{"Message":"hi","UserProfile":"rbxthumb://type=AvatarHeadShot&id=4039873855&w=100&h=100","Name":"fgpqpqht21212","Rank":"Premium"},{"Message":"aup","Name":"AquaHolderCarlYTQ","UserProfile":"rbxthumb://type=AvatarHeadShot&id=3556953880&w=100&h=100","Rank":"User"},{"Message":"im the only one have premium","UserProfile":"rbxthumb://type=AvatarHeadShot&id=4039873855&w=100&h=100","Name":"fgpqpqht21212","Rank":"Premium"}]