[{"Message":"hiii","UserProfile":"rbxthumb://type=AvatarHeadShot&id=4736821268&w=100&h=100","Name":"Roblox_2023free","Rank":"User"},{"Message":"т","Name":"JJFUGN","UserProfile":"rbxthumb://type=AvatarHeadShot&id=1469402880&w=100&h=100","Rank":"Premium"},{"Message":"р","UserProfile":"rbxthumb://type=AvatarHeadShot&id=1469402880&w=100&h=100","Name":"JJFUGN","Rank":"Premium"},{"Message":" до","Name":"JJFUGN","UserProfile":"rbxthumb://type=AvatarHeadShot&id=1469402880&w=100&h=100","Rank":"Premium"},{"Message":"wassup","UserProfile":"rbxthumb://type=AvatarHeadShot&id=1245474440&w=100&h=100","Name":"codebis","Rank":"Premium"},{"Message":"stfu lil bro","Name":"pokehfdc","UserProfile":"rbxthumb://type=AvatarHeadShot&id=1376750707&w=100&h=100","Rank":"User"},{"Message":"lol","UserProfile":"rbxthumb://type=AvatarHeadShot&id=1063207553&w=100&h=100","Name":"jonathanjuanda1234","Rank":"User"},{"Message":"you shut the fuck up poke","Name":"codebis","UserProfile":"rbxthumb://type=AvatarHeadShot&id=1245474440&w=100&h=100","Rank":"Premium"},{"Message":"hi guys","UserProfile":"rbxthumb://type=AvatarHeadShot&id=5246128936&w=100&h=100","Name":"mbmbhy7","Rank":"User"},{"Message":"hello","Name":"dancinginthedark808","UserProfile":"rbxthumb://type=AvatarHeadShot&id=5294024874&w=100&h=100","Rank":"User"},{"Message":"wIt","UserProfile":"rbxthumb://type=AvatarHeadShot&id=5246128936&w=100&h=100","Name":"mbmbhy7","Rank":"User"},{"Message":"I thought u were on my mm2 gme","Name":"mbmbhy7","UserProfile":"rbxthumb://type=AvatarHeadShot&id=5246128936&w=100&h=100","Rank":"User"},{"Message":"anyone Wanna troll or mess the game? ","UserProfile":"rbxthumb://type=AvatarHeadShot&id=1245474440&w=100&h=100","Name":"codebis","Rank":"Premium"},{"Message":"cool script","Name":"Corrupted_filename5","UserProfile":"rbxthumb://type=AvatarHeadShot&id=5233561790&w=100&h=100","Rank":"User"},{"Message":"fuck yw","UserProfile":"rbxthumb://type=AvatarHeadShot&id=5293390208&w=100&h=100","Name":"imnothack7973","Rank":"User"},{"Message":"fuck yall","Name":"imnothack7973","UserProfile":"rbxthumb://type=AvatarHeadShot&id=5293390208&w=100&h=100","Rank":"User"},{"Message":" ruh","UserProfile":"rbxthumb://type=AvatarHeadShot&id=5233561790&w=100&h=100","Name":"Corrupted_filename5","Rank":"User"},{"Message":"t","Name":"Corrupted_filename5","UserProfile":"rbxthumb://type=AvatarHeadShot&id=5233561790&w=100&h=100","Rank":"User"},{"Message":"Lol","UserProfile":"rbxthumb://type=AvatarHeadShot&id=3512911941&w=100&h=100","Name":"U_iud","Rank":"Premium"},{"Message":"lol","Name":"Klaudia_LOL638","UserProfile":"rbxthumb://type=AvatarHeadShot&id=4048312652&w=100&h=100","Rank":"User"},{"Message":"hola","UserProfile":"rbxthumb://type=AvatarHeadShot&id=5027824393&w=100&h=100","Name":"Cristian05442","Rank":"User"},{"Message":"bro","Name":"roanyambi","UserProfile":"rbxthumb://type=AvatarHeadShot&id=974985382&w=100&h=100","Rank":"User"},{"Message":"LOL","UserProfile":"rbxthumb://type=AvatarHeadShot&id=5299489260&w=100&h=100","Name":"HEJKATULENKA463","Rank":"User"},{"Message":".","Name":"Djxbjxjssk","UserProfile":"rbxthumb://type=AvatarHeadShot&id=5119007510&w=100&h=100","Rank":"User"},{"Message":"lol","UserProfile":"rbxthumb://type=AvatarHeadShot&id=4198900005&w=100&h=100","Name":"Juan_ignacioO1","Rank":"User"},{"Message":"hello niggerz","Name":"testyy022","UserProfile":"rbxthumb://type=AvatarHeadShot&id=3053889571&w=100&h=100","Rank":"User"},{"Message":"hello niggers","UserProfile":"rbxthumb://type=AvatarHeadShot&id=3053889571&w=100&h=100","Name":"testyy022","Rank":"User"},{"Message":"hi","Name":"Rayti_bigi","UserProfile":"rbxthumb://type=AvatarHeadShot&id=5163334940&w=100&h=100","Rank":"User"},{"Message":"wasaaaa","UserProfile":"rbxthumb://type=AvatarHeadShot&id=4198900005&w=100&h=100","Name":"Juan_ignacioO1","Rank":"User"},{"Message":"how are you?","Name":"Rayti_bigi","UserProfile":"rbxthumb://type=AvatarHeadShot&id=5163334940&w=100&h=100","Rank":"User"},{"Message":"aaa","UserProfile":"rbxthumb://type=AvatarHeadShot&id=1719111240&w=100&h=100","Name":"RetroJayForever","Rank":"User"}]