[{"Message":"у меня 67к+пасс","UserProfile":"rbxthumb://type=AvatarHeadShot&id=3692463286&w=100&h=100","Name":"ki1xql","Rank":"User"},{"Message":"пизда рулям","Name":"JJFUGN","UserProfile":"rbxthumb://type=AvatarHeadShot&id=1469402880&w=100&h=100","Rank":"Premium"},{"Message":"пизда рулям","UserProfile":"rbxthumb://type=AvatarHeadShot&id=1469402880&w=100&h=100","Name":"JJFUGN","Rank":"Premium"},{"Message":"где год мод находится?","Name":"tt_shwxty2","UserProfile":"rbxthumb://type=AvatarHeadShot&id=3780319759&w=100&h=100","Rank":"User"},{"Message":"где год мод нажол","UserProfile":"rbxthumb://type=AvatarHeadShot&id=3780319759&w=100&h=100","Name":"tt_shwxty2","Rank":"User"},{"Message":"hi","Name":"hwhsgwhshw","UserProfile":"rbxthumb://type=AvatarHeadShot&id=2717275253&w=100&h=100","Rank":"User"},{"Message":"shit","UserProfile":"rbxthumb://type=AvatarHeadShot&id=2988910517&w=100&h=100","Name":"Gggjjvuogfr8","Rank":"User"},{"Message":".","Name":"r5n7r","UserProfile":"rbxthumb://type=AvatarHeadShot&id=3717892259&w=100&h=100","Rank":"User"},{"Message":"GG","UserProfile":"rbxthumb://type=AvatarHeadShot&id=1631894912&w=100&h=100","Name":"vezyn4ik890","Rank":"User"},{"Message":"ggWth is going here?","Name":"vezyn4ik890","UserProfile":"rbxthumb://type=AvatarHeadShot&id=1631894912&w=100&h=100","Rank":"User"},{"Message":"noobs","UserProfile":"rbxthumb://type=AvatarHeadShot&id=2369737264&w=100&h=100","Name":"lil_moonboo","Rank":"User"},{"Message":"L","Name":"lil_moonboo","UserProfile":"rbxthumb://type=AvatarHeadShot&id=2369737264&w=100&h=100","Rank":"User"},{"Message":"fuck","UserProfile":"rbxthumb://type=AvatarHeadShot&id=1469402880&w=100&h=100","Name":"JJFUGN","Rank":"Premium"},{"Message":"da","Name":"JJFUGN","UserProfile":"rbxthumb://type=AvatarHeadShot&id=1469402880&w=100&h=100","Rank":"Premium"},{"Message":"сколько можно получить с премиамом за час","UserProfile":"rbxthumb://type=AvatarHeadShot&id=2727095360&w=100&h=100","Name":"miss_fan77","Rank":"User"},{"Message":"хс","Name":"Artur521Lol2022","UserProfile":"rbxthumb://type=AvatarHeadShot&id=3190963862&w=100&h=100","Rank":"User"},{"Message":"сам не знаю уже вот 7 часов фарм","UserProfile":"rbxthumb://type=AvatarHeadShot&id=1187133424&w=100&h=100","Name":"Dugfttfu","Rank":"Premium"},{"Message":"еще не смотрел","Name":"Dugfttfu","UserProfile":"rbxthumb://type=AvatarHeadShot&id=1187133424&w=100&h=100","Rank":"Premium"},{"Message":"и сколька получил","UserProfile":"rbxthumb://type=AvatarHeadShot&id=3190963862&w=100&h=100","Name":"Artur521Lol2022","Rank":"User"},{"Message":"а стоит его покупать","Name":"Artur521Lol2022","UserProfile":"rbxthumb://type=AvatarHeadShot&id=3190963862&w=100&h=100","Rank":"User"},{"Message":"hi","UserProfile":"rbxthumb://type=AvatarHeadShot&id=1943926636&w=100&h=100","Name":"mkomkoM71","Rank":"User"},{"Message":"апон","Name":"sanzyfu","UserProfile":"rbxthumb://type=AvatarHeadShot&id=5390960095&w=100&h=100","Rank":"User"},{"Message":"а","UserProfile":"rbxthumb://type=AvatarHeadShot&id=5363717927&w=100&h=100","Name":"XHilsy5k","Rank":"Premium"},{"Message":"у кого сколько монет у меня 37к","Name":"XHilsy5k","UserProfile":"rbxthumb://type=AvatarHeadShot&id=5363717927&w=100&h=100","Rank":"Premium"},{"Message":"Hi","UserProfile":"rbxthumb://type=AvatarHeadShot&id=2629946509&w=100&h=100","Name":"nico1234wppl1","Rank":"User"},{"Message":"trade blue seer","Name":"dimannnni","UserProfile":"rbxthumb://type=AvatarHeadShot&id=2913080895&w=100&h=100","Rank":"User"},{"Message":"What","UserProfile":"rbxthumb://type=AvatarHeadShot&id=2629946509&w=100&h=100","Name":"nico1234wppl1","Rank":"User"},{"Message":"baguette","Name":"modz9311","UserProfile":"rbxthumb://type=AvatarHeadShot&id=1552893514&w=100&h=100","Rank":"User"},{"Message":"я рыгаю","UserProfile":"rbxthumb://type=AvatarHeadShot&id=4022128693&w=100&h=100","Name":"itz_lizo4ka11","Rank":"User"},{"Message":"у меня ","Name":"2LayEpic","UserProfile":"rbxthumb://type=AvatarHeadShot&id=1215936703&w=100&h=100","Rank":"User"},{"Message":"50к а 88к потратил на кейсы","UserProfile":"rbxthumb://type=AvatarHeadShot&id=1215936703&w=100&h=100","Name":"2LayEpic","Rank":"User"}]