[{"Message":"читы топ","UserProfile":"rbxthumb://type=AvatarHeadShot&id=1640129482&w=100&h=100","Name":"Timurbayka","Rank":"User"},{"Message":"lol","Name":"CANDYFARM_2023","UserProfile":"rbxthumb://type=AvatarHeadShot&id=5152864595&w=100&h=100","Rank":"User"},{"Message":"боже тп к мардеру и убивает это кайф скрипт","UserProfile":"rbxthumb://type=AvatarHeadShot&id=4090950700&w=100&h=100","Name":"Jcjchjcjcjug","Rank":"User"},{"Message":"зд","Name":"timofeybor2345","UserProfile":"rbxthumb://type=AvatarHeadShot&id=1290687233&w=100&h=100","Rank":"User"},{"Message":"иконку можно двинуть или поставить флюксус по с","UserProfile":"rbxthumb://type=AvatarHeadShot&id=840401472&w=100&h=100","Name":"Geoging","Rank":"User"},{"Message":"иконку можно подвинуть если хотите сделайте в настройкахфлюксус по середине кому медленный автофарм поставьте автоматически","Name":"Geoging","UserProfile":"rbxthumb://type=AvatarHeadShot&id=840401472&w=100&h=100","Rank":"User"},{"Message":"у мя уже 6к я успею 98к набрать?","UserProfile":"rbxthumb://type=AvatarHeadShot&id=3185362035&w=100&h=100","Name":"pdjdhuhuis","Rank":"User"},{"Message":"да","Name":"Geoging","UserProfile":"rbxthumb://type=AvatarHeadShot&id=840401472&w=100&h=100","Rank":"User"},{"Message":"думаю да","UserProfile":"rbxthumb://type=AvatarHeadShot&id=5416965432&w=100&h=100","Name":"Adepte_kchay2024","Rank":"Premium"},{"Message":"ч","Name":"Geoging","UserProfile":"rbxthumb://type=AvatarHeadShot&id=840401472&w=100&h=100","Rank":"User"},{"Message":"не успеешь, что потратишь на боксы либо обменяешь на монеты.","UserProfile":"rbxthumb://type=AvatarHeadShot&id=840401472&w=100&h=100","Name":"Geoging","Rank":"User"},{"Message":"если не успеешь что мало вероятно","Name":"Geoging","UserProfile":"rbxthumb://type=AvatarHeadShot&id=840401472&w=100&h=100","Rank":"User"},{"Message":"а до какого обнова?","UserProfile":"rbxthumb://type=AvatarHeadShot&id=3431355279&w=100&h=100","Name":"Ded_Morozik6you","Rank":"User"},{"Message":"успеешь ещё как времени ещё много","Name":"rtyo890","UserProfile":"rbxthumb://type=AvatarHeadShot&id=2979555466&w=100&h=100","Rank":"User"},{"Message":"обнова до 21 января примерно","UserProfile":"rbxthumb://type=AvatarHeadShot&id=5416965432&w=100&h=100","Name":"Adepte_kchay2024","Rank":"Premium"},{"Message":"надеюсь успею!!","Name":"pdjdhuhuis","UserProfile":"rbxthumb://type=AvatarHeadShot&id=3185362035&w=100&h=100","Rank":"User"},{"Message":"успеешь, попробуй ночью пофармить еще","UserProfile":"rbxthumb://type=AvatarHeadShot&id=5416965432&w=100&h=100","Name":"Adepte_kchay2024","Rank":"Premium"},{"Message":"добавьте авто ресет когда фулл не только за невиннного","Name":"Geoging","UserProfile":"rbxthumb://type=AvatarHeadShot&id=840401472&w=100&h=100","Rank":"User"},{"Message":"еклипси скатился этот лучше","UserProfile":"rbxthumb://type=AvatarHeadShot&id=840401472&w=100&h=100","Name":"Geoging","Rank":"User"},{"Message":"по оптимизации только три часа прошло и капец как лагает","Name":"Geoging","UserProfile":"rbxthumb://type=AvatarHeadShot&id=840401472&w=100&h=100","Rank":"User"},{"Message":"а тут сиди 30 часов потом может вылетит из. зп инета","UserProfile":"rbxthumb://type=AvatarHeadShot&id=840401472&w=100&h=100","Name":"Geoging","Rank":"User"},{"Message":"туттчит еще на сервк выкидывает","Name":"pdjdhuhuis","UserProfile":"rbxthumb://type=AvatarHeadShot&id=3185362035&w=100&h=100","Rank":"User"},{"Message":"меня раньше выкидывало ","UserProfile":"rbxthumb://type=AvatarHeadShot&id=5416965432&w=100&h=100","Name":"Adepte_kchay2024","Rank":"Premium"},{"Message":"я установил другой чит и ща норм, вообще не вылетает ","Name":"Adepte_kchay2024","UserProfile":"rbxthumb://type=AvatarHeadShot&id=5416965432&w=100&h=100","Rank":"Premium"},{"Message":"типа из-за интернета","UserProfile":"rbxthumb://type=AvatarHeadShot&id=3185362035&w=100&h=100","Name":"pdjdhuhuis","Rank":"User"},{"Message":"?","Name":"pdjdhuhuis","UserProfile":"rbxthumb://type=AvatarHeadShot&id=3185362035&w=100&h=100","Rank":"User"},{"Message":"у мя тоже инет шалит","UserProfile":"rbxthumb://type=AvatarHeadShot&id=5416965432&w=100&h=100","Name":"Adepte_kchay2024","Rank":"Premium"},{"Message":"а ненене, там другое, точно не инет","Name":"Adepte_kchay2024","UserProfile":"rbxthumb://type=AvatarHeadShot&id=5416965432&w=100&h=100","Rank":"Premium"},{"Message":"капец попробую сегодня ночью поставить","UserProfile":"rbxthumb://type=AvatarHeadShot&id=3185362035&w=100&h=100","Name":"pdjdhuhuis","Rank":"User"},{"Message":"удачи ","Name":"Adepte_kchay2024","UserProfile":"rbxthumb://type=AvatarHeadShot&id=5416965432&w=100&h=100","Rank":"Premium"},{"Message":"спасибки","UserProfile":"rbxthumb://type=AvatarHeadShot&id=3185362035&w=100&h=100","Name":"pdjdhuhuis","Rank":"User"}]